municipality_lookup/__init__.py
municipality_lookup/database.py
municipality_lookup/instance.py
municipality_lookup/models.py
municipality_lookup/search.py
municipality_lookup/utils.py
municipality_lookup/data/__init__.py
municipality_lookup/data/comuni.csv
municipality_lookup-0.2.2.dist-info/LICENSE
municipality_lookup-0.2.2.dist-info/METADATA
municipality_lookup-0.2.2.dist-info/WHEEL
municipality_lookup-0.2.2.dist-info/top_level.txt
municipality_lookup-0.2.2.dist-info/RECORD
