Metadata-Version: 2.1
Name: municipality-lookup
Version: 0.2.2
Summary: Fuzzy and exact lookup tool for Italian municipalities
Home-page: https://github.com/andrjan1/municipality-lookup
Author: Andrea Iannazzo
Author-email: andrea.iannazzo@gmail.com
Classifier: Development Status :: 4 - Beta
Classifier: Intended Audience :: Developers
Classifier: License :: OSI Approved :: MIT License
Classifier: Programming Language :: Python :: 3
Requires-Python: >=3.8
License-File: LICENSE
Requires-Dist: pandas
Requires-Dist: rapidfuzz
Requires-Dist: importlib-resources >=5.12.0
